pydnp3.cpython-39-x86_64-linux-gnu.so
dnp3_python/__init__.py
dnp3_python/dnp3station/__init__.py
dnp3_python/dnp3station/master.py
dnp3_python/dnp3station/outstation.py
dnp3_python/dnp3station/station_utils.py
dnp3_python/dnp3station/visitors.py
dnp3demo/__main__.py
dnp3demo/control_workflow_demo.py
dnp3demo/data_retrieval_demo.py
dnp3demo/multi_stations_demo.py
dnp3demo/run_master.py
dnp3demo/run_outstation.py
dnp3_python-0.3.0b2.dist-info/LICENSE
dnp3_python-0.3.0b2.dist-info/METADATA
dnp3_python-0.3.0b2.dist-info/WHEEL
dnp3_python-0.3.0b2.dist-info/entry_points.txt
dnp3_python-0.3.0b2.dist-info/top_level.txt
dnp3_python-0.3.0b2.dist-info/RECORD
