Metadata-Version: 2.1
Name: dnp3-python
Version: 0.3.0b2
Summary: pydnp3 -- python binding for opendnp3
Home-page: https://github.com/VOLTTRON/dnp3-python
Author: Volttron Team
Author-email: volttron@pnnl.gov
License: UNKNOWN
Platform: UNKNOWN
License-File: LICENSE
Requires-Dist: argcomplete
